Workbook

Sheet BASE_EMISSORES
A1: Data | B1: Emissor | C1: Setor | D1: Controlador (1=sim, 0=não) | E1: DL/EBITDA | F1: Margem EBITDA | G1: FCO/EBITDA | H1: EBITDA/Resultado Financeiro | I1: Caixa/Divida CP | J1: ROE | K1: Rating Interno | L1: Válido
A2: 45849 | B2: CEMIG | C2: Energia eletrica | D2: 0 | E2: 1 | F2: 0.19 | G2: 0.75 | H2: 1.1 | I2: 1.7833 | J2: 0.0744 | K2: AA+
A3: 45708 | B3: COPEL | C3: Energia eletrica | D3: 0 | E3: 1.4 | F3: 0.25 | G3: 0.6249 | H3: 5.4 | I3: 2.4 | J3: 0.1746 | K3: AA+
A4: 44859 | B4: CPFL | C4: Energia eletrica | D4: 1 | E4: 2 | F4: 0.3 | G4: 0.78 | H4: 5.1 | I4: 0.7 | J4: 0.339 | K4: AAA
A5: 45685 | B5: ELETROBRAS | C5: Energia eletrica | D5: 0 | E5: 1.7 | F5: 0.65 | G5: 0.3785 | H5: 2.1 | I5: 1.8 | J5: 0.102 | K5: AA+
A6: 45594 | B6: ENERGISA | C6: Energia eletrica | D6: 0 | E6: 2.7 | F6: 0.276 | G6: 0.595 | H6: 4.1 | I6: 1.2 | J6: 0.18 | K6: AA
A7: 45945 | B7: EQUATORIAL | C7: Energia eletrica | D7: 0 | E7: 3.2 | F7: 0.29 | G7: 0.2281 | H7: 2.4 | I7: 1.34 | J7: 0.1425 | K7: AA+
A8: 45980 | B8: NEOENERGIA | C8: Energia eletrica | D8: 1 | E8: 3.5 | F8: 0.267 | G8: 0.45 | H8: 2.3 | I8: 1.1 | J8: 0.1312 | K8: AA-
A9: 45727 | B9: SERENA | C9: Energia eletrica | D9: 0 | E9: 5.1 | F9: 0.558 | G9: 0.1731 | H9: 1.9 | I9: 0.7 | J9: 0.0522 | K9: A+
A10: 45849 | B10: TAESA | C10: Energia eletrica | D10: 1 | E10: 5 | F10: 0.85 | G10: 0.4724 | H10: 1.5 | I10: 0.8 | J10: 0.1 | K10: AA+
A11: 45758 | B11: TUPI ENERGIA | C11: Energia eletrica | D11: 0 | E11: 3.41 | F11: 0.47 | G11: 0.645 | H11: 2.51 | I11: 1.48 | J11: 0.016 | K11: A+

Sheet PARAMETROS
B2: Controlador Relevante | E2: DL/EBITDA | H2: Margem EBITDA | K2: FCO/EBITDA | N2: Cobertura de Juros | Q2: Caixa/Divida CP | T2: ROE | W2: Faixas de Pontuação -> Rating
B3: Situação | C3: Pontos | E3: Faixa | F3: Pontos | H3: Faixa | I3: Pontos | K3: Faixa | L3: Pontos | N3: Faixa | O3: Pontos | Q3: Faixa | R3: Pontos | T3: Faixa | U3: Pontos | W3: Score Final | X3: Rating
B4: Sim | C4: -1 | E4: 0 | F4: 1 | H4: 0.1 | I4: 5 | K4: 0.05 | L4: 5 | N4: 1 | O4: 5 | Q4: 0 | R4: 5 | T4: 0 | U4: 5 | W4: 1 | X4: AAA | Y4: 1
B5: Não | C5: 0 | E5: 1 | F5: 2 | H5: 0.2 | I5: 4 | K5: 0.1 | L5: 4 | N5: 1.5 | O5: 4 | Q5: 0.5 | R5: 4 | T5: 0.05 | U5: 4 | W5: 1.5 | X5: AA+
E6: 2 | F6: 3 | H6: 0.3 | I6: 3 | K6: 0.2 | L6: 3 | N6: 2.5 | O6: 3 | Q6: 1 | R6: 3 | T6: 0.1 | U6: 3 | W6: 2 | X6: AA
E7: 3 | F7: 4 | H7: 0.4 | I7: 2 | K7: 0.4 | L7: 2 | N7: 3 | O7: 2 | Q7: 1.5 | R7: 2 | T7: 0.15 | U7: 2 | W7: 2.5 | X7: AA-
E8: 4 | F8: 5 | H8: 0.5 | I8: 1 | K8: 0.6 | L8: 1 | N8: 4 | O8: 1 | Q8: 2 | R8: 1 | T8: 0.2 | U8: 1 | W8: 3 | X8: A+
W9: 3.5 | X9: A
W10: 4 | X10: A-
W11: 4.5 | X11: BBB+
W12: 5 | X12: BBB | Y12: 5
B17: Pesos do Parametro | C17: -> Regressão logística para encontrar os pesos
B18: Indicador | C18: Peso
B19: DL/EBITDA | C19: 0.2
B20: FCO/EBITDA | C20: 0.2
B21: Caixa/Dívida CP | C21: 0.2
B22: Margem EBITDA | C22: 0.15
B23: Cobertura de juros | C23: 0.15
B24: Controlador | C24: 0.05
B25: ROE | C25: 0.05
B29: Logit para encontrar pesos -> Y binária (rating > A = 1; < A = 0), ver o impacto de cada variavel no rating se melhora ou piora

Sheet CALCULO_NOTA
C1: 0.05 | D1: 0.2 | E1: 0.15 | F1: 0.2 | G1: 0.15 | H1: 0.2 | I1: 0.05
A2: A nota das variáveis independentes é calculada a partir da aba parametros, conforme as faixas | J2: Score final é o somatorio de score*peso de cada independente
A3: Emissor | B3: Setor | C3: Controlador (1; -1) | D3: DL/EBITDA | E3: Margem EBITDA | F3: FCO/EBITDA | G3: EBITDA/Resultado financeiro | H3: Caixa/Divida CP | I3: ROE | J3: Score Final (score*peso) | K3: Rating Atribuído | L3: Rating atual
A4: =BASE_EMISSORES!B2 -> CEMIG | B4: =BASE_EMISSORES!C2 -> Energia eletrica | C4: =IF(_xlfn.XLOOKUP(A4,BASE_EMISSORES!B:B,BASE_EMISSORES!D:D)=1,0,-1) -> -1 | D4: =VLOOKUP(_xlfn.XLOOKUP(A4,BASE_EMISSORES!B:B,BASE_EMISSORES!E:E),PARAMETROS!$E$4:$F$8,2,TRUE) -> 2 | E4: =VLOOKUP(_xlfn.XLOOKUP(A4,BASE_EMISSORES!B:B,BASE_EMISSORES!F:F),PARAMETROS!$H$4:$I$8,2,TRUE) -> 5 | F4: =VLOOKUP(_xlfn.XLOOKUP(A4,BASE_EMISSORES!B:B,BASE_EMISSORES!G:G),PARAMETROS!$K$4:$L$8,2,TRUE) -> 1 | G4: =VLOOKUP(_xlfn.XLOOKUP(A4,BASE_EMISSORES!B:B,BASE_EMISSORES!H:H),PARAMETROS!$N$4:$O$8,2,TRUE) -> 5 | H4: =VLOOKUP(_xlfn.XLOOKUP(A4,BASE_EMISSORES!B:B,BASE_EMISSORES!I:I),PARAMETROS!$Q$4:$R$8,2,TRUE) -> 2 | I4: =VLOOKUP(_xlfn.XLOOKUP(A4,BASE_EMISSORES!B:B,BASE_EMISSORES!J:J),PARAMETROS!$T$4:$U$8,2,TRUE) -> 4 | J4: =SUMPRODUCT(C4:I4,$C$1:$I$1) -> 2.65 | K4: =VLOOKUP(J4,PARAMETROS!$W$4:$X$12,2,TRUE) -> AA- | L4: =BASE_EMISSORES!K2 -> AA+
A5: =BASE_EMISSORES!B3 -> COPEL | B5: =BASE_EMISSORES!C3 -> Energia eletrica | C5: =IF(_xlfn.XLOOKUP(A5,BASE_EMISSORES!B:B,BASE_EMISSORES!D:D)=1,0,-1) -> -1 | D5: =VLOOKUP(_xlfn.XLOOKUP(A5,BASE_EMISSORES!B:B,BASE_EMISSORES!E:E),PARAMETROS!$E$4:$F$8,2,TRUE) -> 2 | E5: =VLOOKUP(_xlfn.XLOOKUP(A5,BASE_EMISSORES!B:B,BASE_EMISSORES!F:F),PARAMETROS!$H$4:$I$8,2,TRUE) -> 4 | F5: =VLOOKUP(_xlfn.XLOOKUP(A5,BASE_EMISSORES!B:B,BASE_EMISSORES!G:G),PARAMETROS!$K$4:$L$8,2,TRUE) -> 1 | G5: =VLOOKUP(_xlfn.XLOOKUP(A5,BASE_EMISSORES!B:B,BASE_EMISSORES!H:H),PARAMETROS!$N$4:$O$8,2,TRUE) -> 1 | H5: =VLOOKUP(_xlfn.XLOOKUP(A5,BASE_EMISSORES!B:B,BASE_EMISSORES!I:I),PARAMETROS!$Q$4:$R$8,2,TRUE) -> 1 | I5: =VLOOKUP(_xlfn.XLOOKUP(A5,BASE_EMISSORES!B:B,BASE_EMISSORES!J:J),PARAMETROS!$T$4:$U$8,2,TRUE) -> 2 | J5: =SUMPRODUCT(C5:I5,$C$1:$I$1) -> 1.6 | K5: =VLOOKUP(J5,PARAMETROS!$W$4:$X$12,2,TRUE) -> AA+ | L5: =BASE_EMISSORES!K3 -> AA+
A6: =BASE_EMISSORES!B4 -> CPFL | B6: =BASE_EMISSORES!C4 -> Energia eletrica | C6: =IF(_xlfn.XLOOKUP(A6,BASE_EMISSORES!B:B,BASE_EMISSORES!D:D)=1,0,-1) -> 0 | D6: =VLOOKUP(_xlfn.XLOOKUP(A6,BASE_EMISSORES!B:B,BASE_EMISSORES!E:E),PARAMETROS!$E$4:$F$8,2,TRUE) -> 3 | E6: =VLOOKUP(_xlfn.XLOOKUP(A6,BASE_EMISSORES!B:B,BASE_EMISSORES!F:F),PARAMETROS!$H$4:$I$8,2,TRUE) -> 3 | F6: =VLOOKUP(_xlfn.XLOOKUP(A6,BASE_EMISSORES!B:B,BASE_EMISSORES!G:G),PARAMETROS!$K$4:$L$8,2,TRUE) -> 1 | G6: =VLOOKUP(_xlfn.XLOOKUP(A6,BASE_EMISSORES!B:B,BASE_EMISSORES!H:H),PARAMETROS!$N$4:$O$8,2,TRUE) -> 1 | H6: =VLOOKUP(_xlfn.XLOOKUP(A6,BASE_EMISSORES!B:B,BASE_EMISSORES!I:I),PARAMETROS!$Q$4:$R$8,2,TRUE) -> 4 | I6: =VLOOKUP(_xlfn.XLOOKUP(A6,BASE_EMISSORES!B:B,BASE_EMISSORES!J:J),PARAMETROS!$T$4:$U$8,2,TRUE) -> 1 | J6: =SUMPRODUCT(C6:I6,$C$1:$I$1) -> 2.25 | K6: =VLOOKUP(J6,PARAMETROS!$W$4:$X$12,2,TRUE) -> AA | L6: =BASE_EMISSORES!K4 -> AAA
A7: =BASE_EMISSORES!B5 -> ELETROBRAS | B7: =BASE_EMISSORES!C5 -> Energia eletrica | C7: =IF(_xlfn.XLOOKUP(A7,BASE_EMISSORES!B:B,BASE_EMISSORES!D:D)=1,0,-1) -> -1 | D7: =VLOOKUP(_xlfn.XLOOKUP(A7,BASE_EMISSORES!B:B,BASE_EMISSORES!E:E),PARAMETROS!$E$4:$F$8,2,TRUE) -> 2 | E7: =VLOOKUP(_xlfn.XLOOKUP(A7,BASE_EMISSORES!B:B,BASE_EMISSORES!F:F),PARAMETROS!$H$4:$I$8,2,TRUE) -> 1 | F7: =VLOOKUP(_xlfn.XLOOKUP(A7,BASE_EMISSORES!B:B,BASE_EMISSORES!G:G),PARAMETROS!$K$4:$L$8,2,TRUE) -> 3 | G7: =VLOOKUP(_xlfn.XLOOKUP(A7,BASE_EMISSORES!B:B,BASE_EMISSORES!H:H),PARAMETROS!$N$4:$O$8,2,TRUE) -> 4 | H7: =VLOOKUP(_xlfn.XLOOKUP(A7,BASE_EMISSORES!B:B,BASE_EMISSORES!I:I),PARAMETROS!$Q$4:$R$8,2,TRUE) -> 2 | I7: =VLOOKUP(_xlfn.XLOOKUP(A7,BASE_EMISSORES!B:B,BASE_EMISSORES!J:J),PARAMETROS!$T$4:$U$8,2,TRUE) -> 3 | J7: =SUMPRODUCT(C7:I7,$C$1:$I$1) -> 2.25 | K7: =VLOOKUP(J7,PARAMETROS!$W$4:$X$12,2,TRUE) -> AA | L7: =BASE_EMISSORES!K5 -> AA+
A8: =BASE_EMISSORES!B6 -> ENERGISA | B8: =BASE_EMISSORES!C6 -> Energia eletrica | C8: =IF(_xlfn.XLOOKUP(A8,BASE_EMISSORES!B:B,BASE_EMISSORES!D:D)=1,0,-1) -> -1 | D8: =VLOOKUP(_xlfn.XLOOKUP(A8,BASE_EMISSORES!B:B,BASE_EMISSORES!E:E),PARAMETROS!$E$4:$F$8,2,TRUE) -> 3 | E8: =VLOOKUP(_xlfn.XLOOKUP(A8,BASE_EMISSORES!B:B,BASE_EMISSORES!F:F),PARAMETROS!$H$4:$I$8,2,TRUE) -> 4 | F8: =VLOOKUP(_xlfn.XLOOKUP(A8,BASE_EMISSORES!B:B,BASE_EMISSORES!G:G),PARAMETROS!$K$4:$L$8,2,TRUE) -> 2 | G8: =VLOOKUP(_xlfn.XLOOKUP(A8,BASE_EMISSORES!B:B,BASE_EMISSORES!H:H),PARAMETROS!$N$4:$O$8,2,TRUE) -> 1 | H8: =VLOOKUP(_xlfn.XLOOKUP(A8,BASE_EMISSORES!B:B,BASE_EMISSORES!I:I),PARAMETROS!$Q$4:$R$8,2,TRUE) -> 3 | I8: =VLOOKUP(_xlfn.XLOOKUP(A8,BASE_EMISSORES!B:B,BASE_EMISSORES!J:J),PARAMETROS!$T$4:$U$8,2,TRUE) -> 2 | J8: =SUMPRODUCT(C8:I8,$C$1:$I$1) -> 2.4 | K8: =VLOOKUP(J8,PARAMETROS!$W$4:$X$12,2,TRUE) -> AA | L8: =BASE_EMISSORES!K6 -> AA
A9: =BASE_EMISSORES!B7 -> EQUATORIAL | B9: =BASE_EMISSORES!C7 -> Energia eletrica | C9: =IF(_xlfn.XLOOKUP(A9,BASE_EMISSORES!B:B,BASE_EMISSORES!D:D)=1,0,-1) -> -1 | D9: =VLOOKUP(_xlfn.XLOOKUP(A9,BASE_EMISSORES!B:B,BASE_EMISSORES!E:E),PARAMETROS!$E$4:$F$8,2,TRUE) -> 4 | E9: =VLOOKUP(_xlfn.XLOOKUP(A9,BASE_EMISSORES!B:B,BASE_EMISSORES!F:F),PARAMETROS!$H$4:$I$8,2,TRUE) -> 4 | F9: =VLOOKUP(_xlfn.XLOOKUP(A9,BASE_EMISSORES!B:B,BASE_EMISSORES!G:G),PARAMETROS!$K$4:$L$8,2,TRUE) -> 3 | G9: =VLOOKUP(_xlfn.XLOOKUP(A9,BASE_EMISSORES!B:B,BASE_EMISSORES!H:H),PARAMETROS!$N$4:$O$8,2,TRUE) -> 4 | H9: =VLOOKUP(_xlfn.XLOOKUP(A9,BASE_EMISSORES!B:B,BASE_EMISSORES!I:I),PARAMETROS!$Q$4:$R$8,2,TRUE) -> 3 | I9: =VLOOKUP(_xlfn.XLOOKUP(A9,BASE_EMISSORES!B:B,BASE_EMISSORES!J:J),PARAMETROS!$T$4:$U$8,2,TRUE) -> 3 | J9: =SUMPRODUCT(C9:I9,$C$1:$I$1) -> 3.3 | K9: =VLOOKUP(J9,PARAMETROS!$W$4:$X$12,2,TRUE) -> A+ | L9: =BASE_EMISSORES!K7 -> AA+
A10: =BASE_EMISSORES!B8 -> NEOENERGIA | B10: =BASE_EMISSORES!C8 -> Energia eletrica | C10: =IF(_xlfn.XLOOKUP(A10,BASE_EMISSORES!B:B,BASE_EMISSORES!D:D)=1,0,-1) -> 0 | D10: =VLOOKUP(_xlfn.XLOOKUP(A10,BASE_EMISSORES!B:B,BASE_EMISSORES!E:E),PARAMETROS!$E$4:$F$8,2,TRUE) -> 4 | E10: =VLOOKUP(_xlfn.XLOOKUP(A10,BASE_EMISSORES!B:B,BASE_EMISSORES!F:F),PARAMETROS!$H$4:$I$8,2,TRUE) -> 4 | F10: =VLOOKUP(_xlfn.XLOOKUP(A10,BASE_EMISSORES!B:B,BASE_EMISSORES!G:G),PARAMETROS!$K$4:$L$8,2,TRUE) -> 2 | G10: =VLOOKUP(_xlfn.XLOOKUP(A10,BASE_EMISSORES!B:B,BASE_EMISSORES!H:H),PARAMETROS!$N$4:$O$8,2,TRUE) -> 4 | H10: =VLOOKUP(_xlfn.XLOOKUP(A10,BASE_EMISSORES!B:B,BASE_EMISSORES!I:I),PARAMETROS!$Q$4:$R$8,2,TRUE) -> 3 | I10: =VLOOKUP(_xlfn.XLOOKUP(A10,BASE_EMISSORES!B:B,BASE_EMISSORES!J:J),PARAMETROS!$T$4:$U$8,2,TRUE) -> 3 | J10: =SUMPRODUCT(C10:I10,$C$1:$I$1) -> 3.15 | K10: =VLOOKUP(J10,PARAMETROS!$W$4:$X$12,2,TRUE) -> A+ | L10: =BASE_EMISSORES!K8 -> AA-
A11: =BASE_EMISSORES!B9 -> SERENA | B11: =BASE_EMISSORES!C9 -> Energia eletrica | C11: =IF(_xlfn.XLOOKUP(A11,BASE_EMISSORES!B:B,BASE_EMISSORES!D:D)=1,0,-1) -> -1 | D11: =VLOOKUP(_xlfn.XLOOKUP(A11,BASE_EMISSORES!B:B,BASE_EMISSORES!E:E),PARAMETROS!$E$4:$F$8,2,TRUE) -> 5 | E11: =VLOOKUP(_xlfn.XLOOKUP(A11,BASE_EMISSORES!B:B,BASE_EMISSORES!F:F),PARAMETROS!$H$4:$I$8,2,TRUE) -> 1 | F11: =VLOOKUP(_xlfn.XLOOKUP(A11,BASE_EMISSORES!B:B,BASE_EMISSORES!G:G),PARAMETROS!$K$4:$L$8,2,TRUE) -> 4 | G11: =VLOOKUP(_xlfn.XLOOKUP(A11,BASE_EMISSORES!B:B,BASE_EMISSORES!H:H),PARAMETROS!$N$4:$O$8,2,TRUE) -> 4 | H11: =VLOOKUP(_xlfn.XLOOKUP(A11,BASE_EMISSORES!B:B,BASE_EMISSORES!I:I),PARAMETROS!$Q$4:$R$8,2,TRUE) -> 4 | I11: =VLOOKUP(_xlfn.XLOOKUP(A11,BASE_EMISSORES!B:B,BASE_EMISSORES!J:J),PARAMETROS!$T$4:$U$8,2,TRUE) -> 4 | J11: =SUMPRODUCT(C11:I11,$C$1:$I$1) -> 3.5 | K11: =VLOOKUP(J11,PARAMETROS!$W$4:$X$12,2,TRUE) -> A | L11: =BASE_EMISSORES!K9 -> A+
A12: =BASE_EMISSORES!B10 -> TAESA | B12: =BASE_EMISSORES!C10 -> Energia eletrica | C12: =IF(_xlfn.XLOOKUP(A12,BASE_EMISSORES!B:B,BASE_EMISSORES!D:D)=1,0,-1) -> 0 | D12: =VLOOKUP(_xlfn.XLOOKUP(A12,BASE_EMISSORES!B:B,BASE_EMISSORES!E:E),PARAMETROS!$E$4:$F$8,2,TRUE) -> 5 | E12: =VLOOKUP(_xlfn.XLOOKUP(A12,BASE_EMISSORES!B:B,BASE_EMISSORES!F:F),PARAMETROS!$H$4:$I$8,2,TRUE) -> 1 | F12: =VLOOKUP(_xlfn.XLOOKUP(A12,BASE_EMISSORES!B:B,BASE_EMISSORES!G:G),PARAMETROS!$K$4:$L$8,2,TRUE) -> 2 | G12: =VLOOKUP(_xlfn.XLOOKUP(A12,BASE_EMISSORES!B:B,BASE_EMISSORES!H:H),PARAMETROS!$N$4:$O$8,2,TRUE) -> 4 | H12: =VLOOKUP(_xlfn.XLOOKUP(A12,BASE_EMISSORES!B:B,BASE_EMISSORES!I:I),PARAMETROS!$Q$4:$R$8,2,TRUE) -> 4 | I12: =VLOOKUP(_xlfn.XLOOKUP(A12,BASE_EMISSORES!B:B,BASE_EMISSORES!J:J),PARAMETROS!$T$4:$U$8,2,TRUE) -> 3 | J12: =SUMPRODUCT(C12:I12,$C$1:$I$1) -> 3.1 | K12: =VLOOKUP(J12,PARAMETROS!$W$4:$X$12,2,TRUE) -> A+ | L12: =BASE_EMISSORES!K10 -> AA+
A13: =BASE_EMISSORES!B11 -> TUPI ENERGIA | B13: =BASE_EMISSORES!C11 -> Energia eletrica | C13: =IF(_xlfn.XLOOKUP(A13,BASE_EMISSORES!B:B,BASE_EMISSORES!D:D)=1,0,-1) -> -1 | D13: =VLOOKUP(_xlfn.XLOOKUP(A13,BASE_EMISSORES!B:B,BASE_EMISSORES!E:E),PARAMETROS!$E$4:$F$8,2,TRUE) -> 4 | E13: =VLOOKUP(_xlfn.XLOOKUP(A13,BASE_EMISSORES!B:B,BASE_EMISSORES!F:F),PARAMETROS!$H$4:$I$8,2,TRUE) -> 2 | F13: =VLOOKUP(_xlfn.XLOOKUP(A13,BASE_EMISSORES!B:B,BASE_EMISSORES!G:G),PARAMETROS!$K$4:$L$8,2,TRUE) -> 1 | G13: =VLOOKUP(_xlfn.XLOOKUP(A13,BASE_EMISSORES!B:B,BASE_EMISSORES!H:H),PARAMETROS!$N$4:$O$8,2,TRUE) -> 3 | H13: =VLOOKUP(_xlfn.XLOOKUP(A13,BASE_EMISSORES!B:B,BASE_EMISSORES!I:I),PARAMETROS!$Q$4:$R$8,2,TRUE) -> 3 | I13: =VLOOKUP(_xlfn.XLOOKUP(A13,BASE_EMISSORES!B:B,BASE_EMISSORES!J:J),PARAMETROS!$T$4:$U$8,2,TRUE) -> 5 | J13: =SUMPRODUCT(C13:I13,$C$1:$I$1) -> 2.55 | K13: =VLOOKUP(J13,PARAMETROS!$W$4:$X$12,2,TRUE) -> AA- | L13: =BASE_EMISSORES!K11 -> A+

Sheet NOVO_EMISSOR
B2: Entrada de Dados (Analista imputa aqui) | F2: Conversão para Score | G2: Nota | P2: Indicador | Q2: Peso
B3: Emissor | C3: CPFL | F3: DL/EBITDA | G3: =VLOOKUP(C5,PARAMETROS!E4:F8,2,TRUE) -> 3 | P3: DL/EBITDA | Q3: 0.2
B4: Setor | C4: Energia eletrica | F4: FCO/EBITDA | G4: =VLOOKUP(C6,PARAMETROS!K4:L8,2,TRUE) -> 2 | P4: FCO/EBITDA | Q4: 0.2
B5: DL/EBITDA | C5: 2.1 | F5: Margem EBITDA | G5: =VLOOKUP(C7,PARAMETROS!H4:I8,2,TRUE) -> 3 | P5: Margem EBITDA | Q5: 0.15
B6: FCO/EBITDA | C6: 0.588 | F6: EBITDA/Resultado financeiro | G6: =VLOOKUP(C8,PARAMETROS!N4:O8,2,TRUE) -> 1 | P6: Cobertura de juros | Q6: 0.15
B7: Margem EBITDA | C7: 0.31 | F7: Caixa/Dívida CP | G7: =VLOOKUP(C9,PARAMETROS!Q4:R8,2,TRUE) -> 3 | P7: Caixa/Dívida CP | Q7: 0.2
B8: EBITDA/Resultado financeiro | C8: 4.4 | F8: Controlador (1; -1) | G8: =IF(C10=1,0,-1) -> 0 | P8: Controlador | Q8: 0.05
B9: Caixa/Dívida CP | C9: 1.1 | F9: ROE | G9: =VLOOKUP(C11,PARAMETROS!T4:U8,2,TRUE) -> 1 | P9: ROE | Q9: 0.05
B10: Controlador (1=sim, 0=não) | C10: 1 | F10: Score Final | G10: =SUMPRODUCT(G3:G9,Q3:Q9) -> 2.25
B11: ROE | C11: 23.5 | F11: Rating Atribuído | G11: =VLOOKUP(G10,PARAMETROS!W4:X12,2,TRUE) -> AA | H11: -> ponderado pelos pesos de cada variavel independente
B19: Score Setorial (benchmark)
B21: Setor | C21: =C4 -> Energia eletrica
B22: Média do Setor | C22: =AVERAGEIFS(CALCULO_NOTA!J:J,CALCULO_NOTA!B:B,NOVO_EMISSOR!C21) -> 2.675
B23: Mediana do Setor | C23: {=MEDIAN(_xlfn._xlws.FILTER(CALCULO_NOTA!J4:J13,CALCULO_NOTA!B4:B13=NOVO_EMISSOR!C21))} -> 2.6
B24: Rating Médio | C24: =VLOOKUP(C22,PARAMETROS!W4:X12,2,TRUE) -> AA-
B25: Rating Mediano | C25: =VLOOKUP(C23,PARAMETROS!W4:X12,2,TRUE) -> AA-
B27: Percentil no Setor | C27: =IFERROR(COUNTIFS(CALCULO_NOTA!B4:B13,NOVO_EMISSOR!C21,CALCULO_NOTA!J4:J13,"<="&NOVO_EMISSOR!G10)/COUNTIFS(CALCULO_NOTA!B4:B13,NOVO_EMISSOR!C21),"") -> 0.3 | D27: -> Aqui mostra a posição percentual do emissor dentro do setor. Por exemplo: 30%, o emissor é melhor que 70% do setor.
